{"OutputFileHashSum":"22C24E760BD192A0555B67E8723BBB517E13B1CED07B64B6D993AC97D298C295","Converted":true,"OutputModifyDate":"2020-05-26T07:03:17.3932326Z","Metadatas":[{"CategoryName":"VuGen.Replay","Offset":565,"Length":23,"TypeId":1},{"CategoryName":"VuGen.Replay","Offset":754,"Length":75,"TypeId":2},{"CategoryName":"VuGen.Replay","Offset":3859,"Length":223,"TypeId":3},{"CategoryName":"VuGen.Replay","Offset":8719,"Length":224,"TypeId":3},{"CategoryName":"VuGen.Replay","Offset":10461,"Length":135,"TypeId":2},{"CategoryName":"VuGen.Replay","Offset":10596,"Length":67,"TypeId":2},{"CategoryName":"VuGen.Replay","Offset":17480,"Length":120,"TypeId":3},{"CategoryName":"VuGen.Replay","Offset":39330,"Length":122,"TypeId":3},{"CategoryName":"VuGen.Replay","Offset":42575,"Length":127,"TypeId":2},{"CategoryName":"VuGen.Replay","Offset":42912,"Length":93,"TypeId":2},{"CategoryName":"VuGen.Replay","Offset":49970,"Length":225,"TypeId":3},{"CategoryName":"VuGen.Replay","Offset":53450,"Length":151,"TypeId":2},{"CategoryName":"VuGen.Replay","Offset":53601,"Length":68,"TypeId":2},{"CategoryName":"VuGen.Replay","Offset":55525,"Length":112,"TypeId":3},{"CategoryName":"VuGen.Replay","Offset":56416,"Length":126,"TypeId":2},{"CategoryName":"VuGen.Replay","Offset":58388,"Length":96,"TypeId":2},{"CategoryName":"VuGen.Replay","Offset":66145,"Length":134,"TypeId":3},{"CategoryName":"VuGen.Replay","Offset":66490,"Length":134,"TypeId":3},{"CategoryName":"VuGen.Replay","Offset":66813,"Length":134,"TypeId":3},{"CategoryName":"VuGen.Replay","Offset":67136,"Length":134,"TypeId":3},{"CategoryName":"VuGen.Replay","Offset":67459,"Length":134,"TypeId":3},{"CategoryName":"VuGen.Replay","Offset":68468,"Length":154,"TypeId":2},{"CategoryName":"VuGen.Replay","Offset":68834,"Length":74,"TypeId":2},{"CategoryName":"VuGen.Replay","Offset":70428,"Length":132,"TypeId":2},{"CategoryName":"VuGen.Replay","Offset":70583,"Length":21,"TypeId":1},{"CategoryName":"VuGen.Replay","Offset":70604,"Length":23,"TypeId":1},{"CategoryName":"VuGen.Replay","Offset":70793,"Length":75,"TypeId":2},{"CategoryName":"VuGen.Replay","Offset":73898,"Length":223,"TypeId":3},{"CategoryName":"VuGen.Replay","Offset":77584,"Length":133,"TypeId":3},{"CategoryName":"VuGen.Replay","Offset":77904,"Length":133,"TypeId":3},{"CategoryName":"VuGen.Replay","Offset":78224,"Length":133,"TypeId":3},{"CategoryName":"VuGen.Replay","Offset":79464,"Length":224,"TypeId":3},{"CategoryName":"VuGen.Replay","Offset":81259,"Length":135,"TypeId":2},{"CategoryName":"VuGen.Replay","Offset":81394,"Length":67,"TypeId":2},{"CategoryName":"VuGen.Replay","Offset":84684,"Length":133,"TypeId":3},{"CategoryName":"VuGen.Replay","Offset":85296,"Length":133,"TypeId":3},{"CategoryName":"VuGen.Replay","Offset":85902,"Length":133,"TypeId":3},{"CategoryName":"VuGen.Replay","Offset":86517,"Length":133,"TypeId":3},{"CategoryName":"VuGen.Replay","Offset":87134,"Length":133,"TypeId":3},{"CategoryName":"VuGen.Replay","Offset":87772,"Length":133,"TypeId":3},{"CategoryName":"VuGen.Replay","Offset":88395,"Length":133,"TypeId":3},{"CategoryName":"VuGen.Replay","Offset":89003,"Length":133,"TypeId":3},{"CategoryName":"VuGen.Replay","Offset":89637,"Length":133,"TypeId":3},{"CategoryName":"VuGen.Replay","Offset":90391,"Length":120,"TypeId":3},{"CategoryName":"VuGen.Replay","Offset":112611,"Length":133,"TypeId":3},{"CategoryName":"VuGen.Replay","Offset":117945,"Length":122,"TypeId":3},{"CategoryName":"VuGen.Replay","Offset":121247,"Length":126,"TypeId":2},{"CategoryName":"VuGen.Replay","Offset":121583,"Length":93,"TypeId":2},{"CategoryName":"VuGen.Replay","Offset":129856,"Length":225,"TypeId":3},{"CategoryName":"VuGen.Replay","Offset":134021,"Length":151,"TypeId":2},{"CategoryName":"VuGen.Replay","Offset":134172,"Length":68,"TypeId":2},{"CategoryName":"VuGen.Replay","Offset":136096,"Length":112,"TypeId":3},{"CategoryName":"VuGen.Replay","Offset":136987,"Length":126,"TypeId":2},{"CategoryName":"VuGen.Replay","Offset":138959,"Length":96,"TypeId":2},{"CategoryName":"VuGen.Replay","Offset":147114,"Length":134,"TypeId":3},{"CategoryName":"VuGen.Replay","Offset":147459,"Length":134,"TypeId":3},{"CategoryName":"VuGen.Replay","Offset":147782,"Length":134,"TypeId":3},{"CategoryName":"VuGen.Replay","Offset":148105,"Length":134,"TypeId":3},{"CategoryName":"VuGen.Replay","Offset":148428,"Length":134,"TypeId":3},{"CategoryName":"VuGen.Replay","Offset":149437,"Length":154,"TypeId":2},{"CategoryName":"VuGen.Replay","Offset":149803,"Length":74,"TypeId":2},{"CategoryName":"VuGen.Replay","Offset":151397,"Length":132,"TypeId":2},{"CategoryName":"VuGen.Replay","Offset":151552,"Length":21,"TypeId":1},{"CategoryName":"VuGen.Replay","Offset":151573,"Length":23,"TypeId":1},{"CategoryName":"VuGen.Replay","Offset":151762,"Length":75,"TypeId":2},{"CategoryName":"VuGen.Replay","Offset":154867,"Length":223,"TypeId":3},{"CategoryName":"VuGen.Replay","Offset":158553,"Length":133,"TypeId":3},{"CategoryName":"VuGen.Replay","Offset":158873,"Length":133,"TypeId":3},{"CategoryName":"VuGen.Replay","Offset":159193,"Length":133,"TypeId":3},{"CategoryName":"VuGen.Replay","Offset":160433,"Length":224,"TypeId":3},{"CategoryName":"VuGen.Replay","Offset":162228,"Length":135,"TypeId":2},{"CategoryName":"VuGen.Replay","Offset":162363,"Length":67,"TypeId":2},{"CategoryName":"VuGen.Replay","Offset":165653,"Length":133,"TypeId":3},{"CategoryName":"VuGen.Replay","Offset":166265,"Length":133,"TypeId":3},{"CategoryName":"VuGen.Replay","Offset":166871,"Length":133,"TypeId":3},{"CategoryName":"VuGen.Replay","Offset":167486,"Length":133,"TypeId":3},{"CategoryName":"VuGen.Replay","Offset":168103,"Length":133,"TypeId":3},{"CategoryName":"VuGen.Replay","Offset":168741,"Length":133,"TypeId":3},{"CategoryName":"VuGen.Replay","Offset":169364,"Length":133,"TypeId":3},{"CategoryName":"VuGen.Replay","Offset":169972,"Length":133,"TypeId":3},{"CategoryName":"VuGen.Replay","Offset":170606,"Length":133,"TypeId":3},{"CategoryName":"VuGen.Replay","Offset":171360,"Length":120,"TypeId":3},{"CategoryName":"VuGen.Replay","Offset":193580,"Length":133,"TypeId":3},{"CategoryName":"VuGen.Replay","Offset":198914,"Length":122,"TypeId":3},{"CategoryName":"VuGen.Replay","Offset":202216,"Length":126,"TypeId":2},{"CategoryName":"VuGen.Replay","Offset":202552,"Length":93,"TypeId":2},{"CategoryName":"VuGen.Replay","Offset":210825,"Length":225,"TypeId":3},{"CategoryName":"VuGen.Replay","Offset":214790,"Length":151,"TypeId":2},{"CategoryName":"VuGen.Replay","Offset":214941,"Length":68,"TypeId":2},{"CategoryName":"VuGen.Replay","Offset":216865,"Length":112,"TypeId":3},{"CategoryName":"VuGen.Replay","Offset":217756,"Length":126,"TypeId":2},{"CategoryName":"VuGen.Replay","Offset":219728,"Length":96,"TypeId":2},{"CategoryName":"VuGen.Replay","Offset":227883,"Length":134,"TypeId":3},{"CategoryName":"VuGen.Replay","Offset":228228,"Length":134,"TypeId":3},{"CategoryName":"VuGen.Replay","Offset":228551,"Length":134,"TypeId":3},{"CategoryName":"VuGen.Replay","Offset":228874,"Length":134,"TypeId":3},{"CategoryName":"VuGen.Replay","Offset":229197,"Length":134,"TypeId":3},{"CategoryName":"VuGen.Replay","Offset":230206,"Length":154,"TypeId":2},{"CategoryName":"VuGen.Replay","Offset":230572,"Length":74,"TypeId":2},{"CategoryName":"VuGen.Replay","Offset":232166,"Length":132,"TypeId":2},{"CategoryName":"VuGen.Replay","Offset":232321,"Length":21,"TypeId":1}],"MetadataTypes":[{"CategoryName":"VuGen.Replay","MetadataTypeName":"HP.LR.Vugen.Iteration","Id":1},{"CategoryName":"VuGen.Replay","MetadataTypeName":"HP.LR.Vugen.NotifyTransaction","Id":2},{"CategoryName":"VuGen.Replay","MetadataTypeName":"Utt.Debugger.Warning","Id":3},{"CategoryName":"VuGen.Replay","MetadataTypeName":"Utt.Debugger.Error","Id":4},{"CategoryName":"VuGen.Replay","MetadataTypeName":"HP.LR.Vugen.NotifyAny","Id":5}]}